ilimikudi/__init__.py
ilimikudi/data.py
ilimikudi/databases/merged.db
ilimikudi/datasets/gtb_support_posts.csv
ilimikudi/datasets/merged.csv
ilimikudi/datasets/moniepoint_blog_posts.csv
ilimikudi/datasets/opay_blog_posts.csv
ilimikudi/datasets/paystack_blog_posts.csv
ilimikudi/datasets/paystack_support_posts.csv
ilimikudi-0.3.1.dist-info/METADATA
ilimikudi-0.3.1.dist-info/WHEEL
ilimikudi-0.3.1.dist-info/RECORD
