Metadata-Version: 2.1
Name: ilimikudi
Version: 0.3.1
Summary: Datasets for Gen AI customer care and data processing for Nigerian Banks and Fintech
Author: thelaycon
Author-email: tobitobitobiwhy@gmail.com
Requires-Python: >=3.10,<4.0
Classifier: Programming Language :: Python :: 3
Classifier: Programming Language :: Python :: 3.10
Classifier: Programming Language :: Python :: 3.11
Classifier: Programming Language :: Python :: 3.12
Classifier: Programming Language :: Python :: 3.13
Requires-Dist: drissionpage (>=4.1.0.13,<5.0.0.0)
Requires-Dist: mamaduck (>=1.0.1,<2.0.0)
Requires-Dist: pandas (>=2.2.2,<3.0.0)
Requires-Dist: playwright (>=1.49.1,<2.0.0)
Requires-Dist: tiktoken (>=0.8.0,<0.9.0)
